pycln/__init__.py
pycln/__main__.py
pycln/cli.py
pycln/utils/__init__.py
pycln/utils/_exceptions.py
pycln/utils/_nodes.py
pycln/utils/config.py
pycln/utils/iou.py
pycln/utils/pathu.py
pycln/utils/refactor.py
pycln/utils/regexu.py
pycln/utils/report.py
pycln/utils/scan.py
pycln/utils/transform.py
vendor/custom/__init__.py
vendor/custom/_site.py
pycln-2.6.0.dist-info/METADATA
pycln-2.6.0.dist-info/WHEEL
pycln-2.6.0.dist-info/entry_points.txt
pycln-2.6.0.dist-info/licenses/LICENSE
pycln-2.6.0.dist-info/RECORD
