Metadata-Version: 2.4
Name: pycln
Version: 2.6.0
Summary: A formatter for finding and removing unused import statements.
License: MIT
License-File: LICENSE
Keywords: formatter,linter,quality-assurance,tools,cli
Author: Hadi Alqattan
Author-email: alqattanhadizaki@gmail.com
Requires-Python: >=3.9,<4
Classifier: License :: OSI Approved :: MIT License
Classifier: Programming Language :: Python
Classifier: Programming Language :: Python :: 3
Classifier: Programming Language :: Python :: 3.9
Classifier: Programming Language :: Python :: 3.10
Classifier: Programming Language :: Python :: 3.11
Classifier: Programming Language :: Python :: 3.12
Classifier: Programming Language :: Python :: 3.13
Classifier: Programming Language :: Python :: 3.14
Classifier: Topic :: Utilities
Requires-Dist: libcst (>=0.3.10)
Requires-Dist: pathspec (>=0.9.0)
Requires-Dist: pyyaml (>=5.3.1)
Requires-Dist: tomlkit (>=0.11.1)
Requires-Dist: typer (>=0.4.1)
Project-URL: Homepage, https://hadialqattan.github.io/pycln
Project-URL: Repository, https://github.com/hadialqattan/pycln
